conference_scheduler/__init__.py
conference_scheduler/converter.py
conference_scheduler/resources.py
conference_scheduler/scheduler.py
conference_scheduler/validator.py
conference_scheduler/heuristics/__init__.py
conference_scheduler/heuristics/hill_climber.py
conference_scheduler/heuristics/simulated_annealing.py
conference_scheduler/heuristics/utils.py
conference_scheduler/lp_problem/__init__.py
conference_scheduler/lp_problem/constraints.py
conference_scheduler/lp_problem/objective_functions.py
conference_scheduler/lp_problem/utils.py
conference_scheduler-3.0.1.dist-info/DESCRIPTION.rst
conference_scheduler-3.0.1.dist-info/METADATA
conference_scheduler-3.0.1.dist-info/RECORD
conference_scheduler-3.0.1.dist-info/WHEEL
conference_scheduler-3.0.1.dist-info/metadata.json
conference_scheduler-3.0.1.dist-info/top_level.txt
