Metadata-Version: 2.0
Name: conference-scheduler
Version: 3.0.1
Summary: A Python tool to assist the task of scheduling a conference
Home-page: https://github.com/PyconUK/ConferenceScheduler
Author: Owen Campbell, Vince Knight
Author-email: owen.campbell@tanti.org.uk
License: MIT
Platform: UNKNOWN
Classifier: Programming Language :: Python :: 3.6
Requires-Python: >=3.6
Requires-Dist: numpy
Requires-Dist: pulp
